csa_ai_foundation_model_api_clients/__init__.py
csa_ai_foundation_model_api_clients/csa_ai_foundation_model_api_clients.py
csa_ai_foundation_model_api_clients/ai_client/__init__.py
csa_ai_foundation_model_api_clients/ai_client/chatgpt.py
csa_ai_foundation_model_api_clients/ai_client/claude.py
csa_ai_foundation_model_api_clients/ai_client/gemini.py
csa_ai_foundation_model_api_clients-0.1.24.dist-info/METADATA
csa_ai_foundation_model_api_clients-0.1.24.dist-info/WHEEL
csa_ai_foundation_model_api_clients-0.1.24.dist-info/licenses/LICENSE
csa_ai_foundation_model_api_clients-0.1.24.dist-info/RECORD
