Metadata-Version: 2.3
Name: csa_ai_foundation_model_api_clients
Version: 0.1.24
Summary: Cloud Security Alliance AI Foundation Model API Clients
Project-URL: Homepage, https://github.com/CloudSecurityAlliance/csa-ai-foundation-model-api-clients
Project-URL: Issues, https://github.com/CloudSecurityAlliance/csa-ai-foundation-model-api-clients/issues
Author-email: Kurt Seifried <kseifried@cloudsecurityalliance.org>
License-File: LICENSE
Classifier: License :: OSI Approved :: Apache Software License
Classifier: Operating System :: OS Independent
Classifier: Programming Language :: Python :: 3
Requires-Python: >=3.8
Requires-Dist: anthropic
Requires-Dist: google-generativeai
Requires-Dist: openai
